LICENSE
README.md
setup.cfg
setup.py
semly_webdriver_manager_fork.egg-info/PKG-INFO
semly_webdriver_manager_fork.egg-info/SOURCES.txt
semly_webdriver_manager_fork.egg-info/dependency_links.txt
semly_webdriver_manager_fork.egg-info/requires.txt
semly_webdriver_manager_fork.egg-info/top_level.txt
tests/test_brave_driver.py
tests/test_chrome_driver.py
tests/test_chromium_driver.py
tests/test_custom_http_client.py
tests/test_custom_logger.py
tests/test_downloader.py
tests/test_edge_driver.py
tests/test_firefox_manager.py
tests/test_ie_driver.py
tests/test_opera_manager.py
tests/test_silent_global_logs.py
tests/test_utils.py
webdriver_manager/__init__.py
webdriver_manager/chrome.py
webdriver_manager/firefox.py
webdriver_manager/microsoft.py
webdriver_manager/opera.py
webdriver_manager/py.typed
webdriver_manager/core/__init__.py
webdriver_manager/core/archive.py
webdriver_manager/core/config.py
webdriver_manager/core/constants.py
webdriver_manager/core/download_manager.py
webdriver_manager/core/driver.py
webdriver_manager/core/driver_cache.py
webdriver_manager/core/file_manager.py
webdriver_manager/core/http.py
webdriver_manager/core/logger.py
webdriver_manager/core/manager.py
webdriver_manager/core/os_manager.py
webdriver_manager/core/utils.py
webdriver_manager/drivers/__init__.py
webdriver_manager/drivers/chrome.py
webdriver_manager/drivers/edge.py
webdriver_manager/drivers/firefox.py
webdriver_manager/drivers/ie.py
webdriver_manager/drivers/opera.py